{
    "asset": {
        "format": "png",
        "id": "bbce442c9037306805aa3709ae4cd13c",
        "name": "frame-0136.png",
        "path": "file:C:/Users/ioannisb/Documents/Development/AITrainingImages/OUT/frame-0136.png",
        "size": {
            "width": 640,
            "height": 480
        },
        "state": 2,
        "type": 1
    },
    "regions": [
        {
            "id": "OyY0VMGL0",
            "type": "RECTANGLE",
            "tags": [
                "Impact"
            ],
            "boundingBox": {
                "height": 22.491441127232143,
                "width": 27.957165082976445,
                "left": 286.81799551659526,
                "top": 286.3542898995536
            },
            "points": [
                {
                    "x": 286.81799551659526,
                    "y": 286.3542898995536
                },
                {
                    "x": 314.77516059957173,
                    "y": 286.3542898995536
                },
                {
                    "x": 314.77516059957173,
                    "y": 308.8457310267857
                },
                {
                    "x": 286.81799551659526,
                    "y": 308.8457310267857
                }
            ]
        },
        {
            "id": "tUvBrnjFl",
            "type": "RECTANGLE",
            "tags": [
                "Satellite"
            ],
            "boundingBox": {
                "height": 20.297147042410714,
                "width": 25.21630754817987,
                "left": 414.543880487152,
                "top": 206.81143275669643
            },
            "points": [
                {
                    "x": 414.543880487152,
                    "y": 206.81143275669643
                },
                {
                    "x": 439.76018803533185,
                    "y": 206.81143275669643
                },
                {
                    "x": 439.76018803533185,
                    "y": 227.10857979910713
                },
                {
                    "x": 414.543880487152,
                    "y": 227.10857979910713
                }
            ]
        }
    ],
    "version": "2.2.0"
}