{
    "asset": {
        "format": "png",
        "id": "7bbf74815a6eeb78ac5d5413bf975bce",
        "name": "00000085.png",
        "path": "file:C:/Users/ioannisb/Documents/Development/AITrainingImages/OUT/00000085.png",
        "size": {
            "width": 880,
            "height": 720
        },
        "state": 2,
        "type": 1
    },
    "regions": [
        {
            "id": "C3iHQSVNG",
            "type": "RECTANGLE",
            "tags": [
                "Impact"
            ],
            "boundingBox": {
                "height": 55.131434849330354,
                "width": 58.4608061494883,
                "left": 244.22573727613303,
                "top": 391.68001883370533
            },
            "points": [
                {
                    "x": 244.22573727613303,
                    "y": 391.68001883370533
                },
                {
                    "x": 302.6865434256213,
                    "y": 391.68001883370533
                },
                {
                    "x": 302.6865434256213,
                    "y": 446.81145368303567
                },
                {
                    "x": 244.22573727613303,
                    "y": 446.81145368303567
                }
            ]
        },
        {
            "id": "317vSOiub",
            "type": "RECTANGLE",
            "tags": [
                "Shadow"
            ],
            "boundingBox": {
                "height": 48.54858398437499,
                "width": 46.933308205409354,
                "left": 617.2222536321271,
                "top": 394.97142857142853
            },
            "points": [
                {
                    "x": 617.2222536321271,
                    "y": 394.97142857142853
                },
                {
                    "x": 664.1555618375365,
                    "y": 394.97142857142853
                },
                {
                    "x": 664.1555618375365,
                    "y": 443.52001255580353
                },
                {
                    "x": 617.2222536321271,
                    "y": 443.52001255580353
                }
            ]
        },
        {
            "id": "O_l07Vlt9",
            "type": "RECTANGLE",
            "tags": [
                "Satellite"
            ],
            "boundingBox": {
                "height": 59.245689174107135,
                "width": 57.63742690058479,
                "left": 764.6093378792032,
                "top": 394.14858398437497
            },
            "points": [
                {
                    "x": 764.6093378792032,
                    "y": 394.14858398437497
                },
                {
                    "x": 822.246764779788,
                    "y": 394.14858398437497
                },
                {
                    "x": 822.246764779788,
                    "y": 453.3942731584821
                },
                {
                    "x": 764.6093378792032,
                    "y": 453.3942731584821
                }
            ]
        }
    ],
    "version": "2.2.0"
}