{
    "asset": {
        "format": "jpg",
        "id": "9669c7622926bcc86b8e816b804c645f",
        "name": "00000713.jpg",
        "path": "file:C:/Users/ioannisb/Documents/Development/AITrainingImages/OUT/00000713.jpg",
        "size": {
            "width": 1097,
            "height": 878
        },
        "state": 2,
        "type": 1
    },
    "regions": [
        {
            "id": "WEk8Ti_UH",
            "type": "RECTANGLE",
            "tags": [
                "Shadow"
            ],
            "boundingBox": {
                "height": 32.10968366350446,
                "width": 31.127673465545445,
                "left": 499.5649037655758,
                "top": 548.8754745047432
            },
            "points": [
                {
                    "x": 499.5649037655758,
                    "y": 548.8754745047432
                },
                {
                    "x": 530.6925772311213,
                    "y": 548.8754745047432
                },
                {
                    "x": 530.6925772311213,
                    "y": 580.9851581682477
                },
                {
                    "x": 499.5649037655758,
                    "y": 580.9851581682477
                }
            ]
        },
        {
            "id": "8YS5FtF-x",
            "type": "RECTANGLE",
            "tags": [
                "Satellite"
            ],
            "boundingBox": {
                "height": 30.85547450474323,
                "width": 28.35062623187654,
                "left": 532.7008611823111,
                "top": 563.1742857142857
            },
            "points": [
                {
                    "x": 532.7008611823111,
                    "y": 563.1742857142857
                },
                {
                    "x": 561.0514874141877,
                    "y": 563.1742857142857
                },
                {
                    "x": 561.0514874141877,
                    "y": 594.029760219029
                },
                {
                    "x": 532.7008611823111,
                    "y": 594.029760219029
                }
            ]
        }
    ],
    "version": "2.2.0"
}